sdpchainpy/__init__.py
sdpchainpy/argument_parser.py
sdpchainpy/process_steps.py
sdpchainpy/sdpcat.py
sdpchainpy/sdpstep.py
sdpchainpy/version.py
sdpchainpy-1.0.1.dist-info/LICENSE.txt
sdpchainpy-1.0.1.dist-info/METADATA
sdpchainpy-1.0.1.dist-info/WHEEL
sdpchainpy-1.0.1.dist-info/entry_points.txt
sdpchainpy-1.0.1.dist-info/top_level.txt
sdpchainpy-1.0.1.dist-info/RECORD
