Metadata-Version: 2.1
Name: sdpchainpy
Version: 1.0.1
Summary: SDPCHAIN provenance system
Home-page: https://github.com/WayneCrawford/sdpchainpy
Author: Wayne Crawford
Author-email: crawford@ipgp.fr
Keywords: provencance,data,metadata
Classifier: Development Status :: 4 - Beta
Classifier: Environment :: Console
Classifier: Intended Audience :: Science/Research
Classifier: Intended Audience :: Developers
Classifier: License :: OSI Approved :: GNU General Public License v3 (GPLv3)
Classifier: Natural Language :: English
Classifier: Operating System :: OS Independent
Classifier: Programming Language :: Python :: 3.9
Classifier: Topic :: Scientific/Engineering
Classifier: Topic :: Scientific/Engineering :: Physics
Requires-Python: >=3.8
License-File: LICENSE.txt
Requires-Dist: progress (>=1.5)
